tools/auxiliary.py
tools/s3tools.py
tools/exceptions.py
tools/messaging.py
tools/persistence.py
tools/__init__.py
CLAUDE_tools-0.1.14a1.dist-info/WHEEL
CLAUDE_tools-0.1.14a1.dist-info/RECORD
CLAUDE_tools-0.1.14a1.dist-info/DESCRIPTION.rst
CLAUDE_tools-0.1.14a1.dist-info/METADATA
CLAUDE_tools-0.1.14a1.dist-info/top_level.txt
CLAUDE_tools-0.1.14a1.dist-info/metadata.json
receiver/__init__.py
