Metadata-Version: 2.0
Name: CLAUDE-tools
Version: 0.1.14a1
Summary: Tools package, which is used by workers scripts
Home-page: UNKNOWN
Author: Andrei
Author-email: karandash8@gmail.com
License: GPLv2
Keywords: claude tools
Platform: UNKNOWN
Classifier: Development Status :: 3 - Alpha
Classifier: Intended Audience :: Developers
Classifier: Topic :: Software Development :: Libraries
Classifier: License :: OSI Approved :: GNU General Public License v2 (GPLv2)
Classifier: Programming Language :: Python :: 2.7
Requires-Dist: kombu
Requires-Dist: netifaces (==0.10.4)
Requires-Dist: boto (==2.20.1)
